waveletec/__init__.py
waveletec/cec_handler.py
waveletec/handler.py
waveletec/version.py
waveletec/_core/__init__.py
waveletec/_core/addons.py
waveletec/_core/coimbra2024_scripts.py
waveletec/_core/commons.py
waveletec/_core/corrections.py
waveletec/_core/eddypro_tools.py
waveletec/_core/meteo.py
waveletec/_core/partition.py
waveletec/_core/wavelet_functions.py
waveletec/_core/wavelet_misc.py
waveletec-1.2.0.4.dist-info/LICENSE
waveletec-1.2.0.4.dist-info/METADATA
waveletec-1.2.0.4.dist-info/WHEEL
waveletec-1.2.0.4.dist-info/top_level.txt
waveletec-1.2.0.4.dist-info/RECORD
