Metadata-Version: 2.1
Name: waveletec
Version: 1.2.0.4
Summary: Wavelet-based Eddy Covariance Written by pedrohenriquecoimbra
Home-page: https://github.com/pedrohenriquecoimbra/wavelete-ec
Author: Pedro Henrique Coimbra
Author-email: pedro-henrique.herig-coimbra@inrae.fr
License: MIT
Keywords: EC,partitionning,wavelet
Platform: any
Classifier: Development Status :: 4 - Beta
Classifier: Environment :: Other Environment
Classifier: Framework :: Jupyter
Classifier: Intended Audience :: Science/Research
Classifier: Programming Language :: Python
Classifier: Programming Language :: Python :: 3
Classifier: Programming Language :: Python :: 3.8
Classifier: Programming Language :: Python :: 3.9
Classifier: Programming Language :: Python :: 3.10
Classifier: Programming Language :: Python :: 3.11
Classifier: Programming Language :: Python :: 3.12
Classifier: Programming Language :: Python :: 3.13
Classifier: Programming Language :: Python :: 3.14
Classifier: Topic :: Other/Nonlisted Topic
Requires-Python: >=3.8
License-File: LICENSE
Requires-Dist: pandas (>=2.0.0)
Requires-Dist: matplotlib (>=3.1.0)
Requires-Dist: numpy (>=1.24)
Requires-Dist: PyWavelets (>=1.4.0)
Requires-Dist: scipy (>=1.10.0)
Requires-Dist: scikit-learn
Requires-Dist: PyYAML
